ALU.v
module ALU(num1, num2, opcode, result, zero);
    input [15:0] num1; // 16 bit register inputs to ALU
    input [15:0] num2;
    input [3:0] opcode; // 4 bit operation code
    output reg [15:0] result;
    output zero;

    // wire zero, carry, overflow, negative;

    always @(num1 or num2 or opcode)
        case (opcode)
            4'b0001: result = num1 + num2; // ADD
            4'b0010: result = num1 - num2; // SUB
            4'b0011: result = num1 & num2; // AND
            4'b0100: result = num1 | num2;  // OR
            4'b0101: result = num1 ^ num2;  // XOR
            4'b0110: result = ~num1; // NOT the first register
            default: result = num1;         // default case incase opcode is not any of the above -- bypass simply give num1
        endcase 

    assign zero = (result == 0);


endmodule

tb/ALU_tb.v
`include "ALU.v"
module ALU_tb;
    reg [15:0] num1, num2;
    reg [3:0] opcode;
    wire [15:0] result;
    wire zero;

    ALU myALU(.num1(num1), .num2(num2), .opcode(opcode), .result(result), .zero(zero));

    initial begin
        $dumpfile("simulations/alu_wavedata.vcd");
		$dumpvars(0, ALU_tb);


        // ------- ADD TEST ---------
        #10 // 9 + 3
        $display("Test Case: ADD 9 + 3");
        num1 = 16'd9; // 1001
        num2 = 16'd3; // 0011
        opcode = 4'b0001; // add

        // test zero flag -> 5 + (-5)
        $display("Test Case: ADD 5 + -5");
        #10
        num1 = 16'd5;
        num2 = 16'hFFFB; // -5 in 2's complement
        opcode = 4'b0001;


        // ------- SUB TEST ---------
        #10 // 11 - 3
        $display("Test Case: SUB 11 - 3");
        num1 = 16'd11;
        num2 = 16'd3;
        opcode = 4'b0010; // sub

        // test zero flag -> 5 - 5
        #10
        $display("Test Case: SUB Zero flag 5 - 5");
        num1 = 16'd5;
        num2 = 16'd5;
        opcode = 4'b0010;


        // ------- AND TEST ---------
        #10
        $display("Test Case: AND 15 & 7"); // 15 (0...1111), 7 (0...0111) -> 7 (0...0111)
        num1 = 16'hF;
        num2 = 16'h7;
        opcode = 4'b0011; // AND

        // ------- OR TEST ---------
        #10
        $display("Test Case: OR 15 | 7"); // 15 (0...1111), 7 (0...0111) -> 15 (0...1111)
        num1 = 16'hF;
        num2 = 16'h7;
        opcode = 4'b0100; // OR

        // ------- XOR TEST ---------
        #10
        $display("Test Case: XOR 15 ^ 7"); // 15 (0...1111), 7 (0...0111) -> 8 (0...1000)
        num1 = 16'hF;
        num2 = 16'h7;
        opcode = 4'b0101; // xor

        // ------- NOT TEST ---------
        #10
        $display("Test Case: NOT 0xF000"); // 0xF000 (1111...) -> 0x0FFF (0000...)
        num1 = 16'hF;
        opcode = 4'b0110; // not

        // ------- Default Case Unused Operator TEST ---------
        $display("Test Case: Default Opcode");
        num1 = 16'hABCD;
        num2 = 16'h1234;
        opcode = 4'b1111; // Unused opcode

        // Finished sim
        #10;
        $finish;
    
    end


endmodule

sim/waveforms/alu_wavedata.vcd
$date
	Thu Nov 20 19:26:30 2025
$end
$version
	Icarus Verilog
$end
$timescale
	1s
$end
$scope module ALU_tb $end
$var wire 1 ! zero $end
$var wire 16 " result [15:0] $end
$var reg 16 # num1 [15:0] $end
$var reg 16 $ num2 [15:0] $end
$var reg 4 % opcode [3:0] $end
$scope module myALU $end
$var wire 16 & num1 [15:0] $end
$var wire 16 ' num2 [15:0] $end
$var wire 4 ( opcode [3:0] $end
$var wire 1 ! zero $end
$var reg 16 ) result [15:0] $end
$upscope $end
$upscope $end
$enddefinitions $end
$comment Show the parameter values. $end
$dumpall
$end
#0
$dumpvars
bx )
bx (
bx '
bx &
bx %
bx $
bx #
bx "
x!
$end
#10
0!
b1100 "
b1100 )
b1 %
b1 (
b11 $
b11 '
b1001 #
b1001 &
#20
1!
b0 "
b0 )
b1111111111111011 $
b1111111111111011 '
b101 #
b101 &
#30
0!
b1000 "
b1000 )
b10 %
b10 (
b11 $
b11 '
b1011 #
b1011 &
#40
1!
b0 "
b0 )
b101 $
b101 '
b101 #
b101 &
#50
0!
b111 "
b111 )
b11 %
b11 (
b111 $
b111 '
b1111 #
b1111 &
#60
b1111 "
b1111 )
b100 %
b100 (
#70
b1000 "
b1000 )
b101 %
b101 (
#80
b1010101111001101 "
b1010101111001101 )
b1001000110100 $
b1001000110100 '
b1010101111001101 #
b1010101111001101 &
b1111 %
b1111 (
