control_unit.v
// Control Unit for 16-bit RISC (multi-cycle, von Neumann, single-port memory)
module control_unit (
    input  wire        clk,
    input  wire        reset,

    // Datapath feedback
    input  wire [3:0]  opcode,    // IR[15:12]
    input  wire        zero,      // ALU zero flag (for BEQZ)

    // Control outputs to datapath
    output reg         IRload,
    output reg         Aload,
    output reg         Bload,
    output reg         ALUOutLoad,
    output reg         MDRload,
    output reg         RegWrite,

    output reg         MemRead,
    output reg         MemWrite,
    output reg         MemToReg,  // 0: ALUOut -> RF ; 1: MDR -> RF

    output reg  [1:0]  ALUSrcA,   // 00: PC, 01: A, 10: 0, 11: reserved
    output reg  [1:0]  ALUSrcB,   // 00: B, 01: +1, 10: imm, 11: reserved
    output reg  [2:0]  ALUOp,     // 0=ADD,1=SUB,2=AND,3=OR,4=XOR,5=PASSB

    output reg         PCWrite,
    output reg  [1:0]  PCSel,     // 00: ALUOut (PC+1), 01: ALUOut (branch target), 10: jump immediate
    output reg         AddrSel,   // 0: PC -> mem.addr, 1: ALUOut -> mem.addr

    output reg         Halt       // stop execution
);

    // ------------ Opcode map ------------
    localparam [3:0] OP_ADD  = 4'h0;
    localparam [3:0] OP_SUB  = 4'h1;
    localparam [3:0] OP_AND  = 4'h2;
    localparam [3:0] OP_OR   = 4'h3;
    localparam [3:0] OP_XOR  = 4'h4;
    localparam [3:0] OP_LDI  = 4'h5;
    localparam [3:0] OP_LD   = 4'h6;
    localparam [3:0] OP_ST   = 4'h7;
    localparam [3:0] OP_BEQZ = 4'h8;
    localparam [3:0] OP_JMP  = 4'h9;
    localparam [3:0] OP_HLT  = 4'hF;

    // ------------ ALU operations ------------
    localparam [2:0] ALU_ADD   = 3'd0;
    localparam [2:0] ALU_SUB   = 3'd1;
    localparam [2:0] ALU_AND   = 3'd2;
    localparam [2:0] ALU_OR    = 3'd3;
    localparam [2:0] ALU_XOR   = 3'd4;
    localparam [2:0] ALU_PASSB = 3'd5;

    // ------------ FSM states (Verilog-2001) ------------
    localparam [3:0]
        S_IF1    = 4'd0,   // start fetch
        S_IF2    = 4'd1,   // latch IR, PC <- PC+1
        S_ID     = 4'd2,   // decode, reg fetch, resolve beqz/jmp
        S_EX_R   = 4'd3,   // ALU A op B -> ALUOut
        S_WB_R   = 4'd4,   // RegWrite from ALUOut
        S_EX_LDI = 4'd5,   // ALU PASSB(imm) -> ALUOut
        S_WB_LDI = 4'd6,   // RegWrite from ALUOut
        S_EA_LD  = 4'd7,   // effective address for LD
        S_MEM_LD = 4'd8,   // MemRead -> MDR
        S_WB_LD  = 4'd9,   // RegWrite from MDR
        S_EA_ST  = 4'd10,  // effective address for ST
        S_MEM_ST = 4'd11,  // MemWrite
        S_HALT   = 4'd15;

    reg [3:0] state;
    reg [3:0] next;

    // ------------ Sequential: state register ------------
    always @(posedge clk or posedge reset) begin
        if (reset)
            state <= S_IF1;
        else
            state <= next;
    end

    // ------------ Combinational: defaults + outputs + next-state ------------
    always @* begin
        // defaults (deassert everything unless stated otherwise)
        IRload     = 1'b0;
        Aload      = 1'b0;
        Bload      = 1'b0;
        ALUOutLoad = 1'b0;
        MDRload    = 1'b0;
        RegWrite   = 1'b0;

        MemRead    = 1'b0;
        MemWrite   = 1'b0;
        MemToReg   = 1'b0;

        ALUSrcA    = 2'b00;  // default A = PC
        ALUSrcB    = 2'b00;  // default B = reg B
        ALUOp      = ALU_ADD;

        PCWrite    = 1'b0;
        PCSel      = 2'b00;  // from ALUOut
        AddrSel    = 1'b0;   // PC -> mem.addr
        Halt       = 1'b0;

        next       = state;

        case (state)
            // ------- IF1: start instruction fetch -------
            S_IF1: begin
                AddrSel    = 1'b0;      // mem.addr <= PC
                MemRead    = 1'b1;      // begin read
                // Prepare PC+1 in ALUOut
                ALUSrcA    = 2'b00;     // A=PC
                ALUSrcB    = 2'b01;     // +1
                ALUOp      = ALU_ADD;
                ALUOutLoad = 1'b1;      // ALUOut <- PC+1
                next       = S_IF2;
            end

            // ------- IF2: latch IR, commit PC <- PC+1 -------
            S_IF2: begin
                MemRead  = 1'b1;
                IRload   = 1'b1;        // IR <- mem.out
                PCWrite  = 1'b1;        // PC <- ALUOut (PC+1)
                PCSel    = 2'b00;
                next     = S_ID;
            end

            // ------- ID: decode, read regfile, resolve BEQZ/JMP -------
            S_ID: begin
                Aload = 1'b1;           // A <- Reg[rs]
                Bload = 1'b1;           // B <- Reg[rt]

                // Precompute branch target for BEQZ: PC + imm
                if (opcode == OP_BEQZ) begin
                    ALUSrcA    = 2'b00; // PC
                    ALUSrcB    = 2'b10; // imm
                    ALUOp      = ALU_ADD;
                    ALUOutLoad = 1'b1;  // ALUOut <- PC+imm
                end

                // Route by opcode (resolve JMP/BEQZ here)
                if (opcode == OP_ADD || opcode == OP_SUB ||
                    opcode == OP_AND || opcode == OP_OR  ||
                    opcode == OP_XOR) begin
                    next = S_EX_R;
                end
                else if (opcode == OP_LDI) begin
                    next = S_EX_LDI;
                end
                else if (opcode == OP_LD) begin
                    next = S_EA_LD;
                end
                else if (opcode == OP_ST) begin
                    next = S_EA_ST;
                end
                else if (opcode == OP_BEQZ) begin
                    if (zero) begin
                        PCWrite = 1'b1; PCSel = 2'b01; // PC <- ALUOut (branch target)
                    end
                    next = S_IF1;
                end
                else if (opcode == OP_JMP) begin
                    PCWrite = 1'b1; PCSel = 2'b10;     // PC <- jump immediate (from datapath)
                    next    = S_IF1;
                end
                else if (opcode == OP_HLT) begin
                    Halt = 1'b1;
                    next = S_HALT;
                end
                else begin
                    next = S_IF1; // default NOP
                end
            end

            // ------- R-type execute -------
            S_EX_R: begin
                // MemRead    = 1'b1;   // REMOVE: no memory access in R-execute
                ALUSrcA    = 2'b01;     // A
                ALUSrcB    = 2'b00;     // B
                case (opcode)
                OP_ADD: ALUOp = ALU_ADD;
                OP_SUB: ALUOp = ALU_SUB;
                OP_AND: ALUOp = ALU_AND;
                OP_OR : ALUOp = ALU_OR;
                OP_XOR: ALUOp = ALU_XOR;
                default: ALUOp = ALU_ADD;
                endcase
                ALUOutLoad = 1'b1;
                next       = S_WB_R;
            end

            // ------- R-type write-back -------
            S_WB_R: begin
                // MemRead  = 1'b1;     // REMOVE
                RegWrite = 1'b1;        // ALUOut -> RF
                MemToReg = 1'b0;
                next     = S_IF1;
            end

            // ------- LDI execute -------
            S_EX_LDI: begin
                // MemRead    = 1'b1;   // REMOVE
                ALUSrcA    = 2'b10;     // 0
                ALUSrcB    = 2'b10;     // imm
                ALUOp      = ALU_PASSB;
                ALUOutLoad = 1'b1;
                next       = S_WB_LDI;
            end

            // ------- LDI write-back -------
            S_WB_LDI: begin
                // MemRead  = 1'b1;     // REMOVE
                RegWrite = 1'b1;
                MemToReg = 1'b0;        // ALUOut
                next     = S_IF1;
            end

            // ------- LD effective address -------
            S_EA_LD: begin
                // no MemRead here (address calc only)
                ALUSrcA    = 2'b10;     // 0
                ALUSrcB    = 2'b10;     // imm
                ALUOp      = ALU_PASSB;
                ALUOutLoad = 1'b1;
                next       = S_MEM_LD;
            end

            // ------- LD memory read -------
            S_MEM_LD: begin
                AddrSel = 1'b1;         // mem.addr <= ALUOut
                MemRead = 1'b1;         // <-- keep
                MDRload = 1'b1;
                next    = S_WB_LD;
            end

            // ------- LD write-back -------
            S_WB_LD: begin
                RegWrite = 1'b1;
                MemToReg = 1'b1;        // MDR -> RF
                next     = S_IF1;
            end

            // ------- ST effective address -------
            S_EA_ST: begin
                // no MemRead here (address calc only)
                ALUSrcA    = 2'b10;     // 0
                ALUSrcB    = 2'b10;     // imm
                ALUOp      = ALU_PASSB;
                ALUOutLoad = 1'b1;
                next       = S_MEM_ST;
            end

            // ------- ST memory write -------
            S_MEM_ST: begin
                AddrSel  = 1'b1;        // mem.addr <= ALUOut
                MemRead  = 1'b0;        // <-- FORCE 0
                MemWrite = 1'b1;        // write B to memory for one full cycle
                next     = S_IF1;
            end

            // ------- Halt -------
            S_HALT: begin
                Halt = 1'b1;
                next = S_HALT;                      // stay until reset
            end

            default: begin
                next = S_IF1;
            end
        endcase
    end

endmodule

control_unit_tb.v
`include "control_unit.v"

module tb_control_unit;

  // Clock/reset
  reg clk   = 0;
  reg reset = 1;

  // Datapath feedback driven by TB
  reg  [3:0] opcode;
  reg        zero;

  // Control outputs under test
  wire       IRload, Aload, Bload, ALUOutLoad, MDRload, RegWrite;
  wire       MemRead, MemWrite, MemToReg;
  wire [1:0] ALUSrcA, ALUSrcB;
  wire [2:0] ALUOp;
  wire       PCWrite;
  wire [1:0] PCSel;
  wire       AddrSel;
  wire       Halt;
  
  // needed for 6) BEQZ taken - check to look for PCWrite=1, PCSel=01 a couple cycles later
  integer k;
  reg seen_branch;

  // Instantiate DUT
  control_unit dut (
    .clk(clk),
    .reset(reset),
    .opcode(opcode),
    .zero(zero),

    .IRload(IRload),
    .Aload(Aload),
    .Bload(Bload),
    .ALUOutLoad(ALUOutLoad),
    .MDRload(MDRload),
    .RegWrite(RegWrite),

    .MemRead(MemRead),
    .MemWrite(MemWrite),
    .MemToReg(MemToReg),

    .ALUSrcA(ALUSrcA),
    .ALUSrcB(ALUSrcB),
    .ALUOp(ALUOp),

    .PCWrite(PCWrite),
    .PCSel(PCSel),
    .AddrSel(AddrSel),

    .Halt(Halt)
  );

  // Clock: 10ns period
  always #5 clk = ~clk;

  // Local copies of opcode encodings (match DUT)
  localparam [3:0]
    OP_ADD  = 4'h0,
    OP_SUB  = 4'h1,
    OP_AND  = 4'h2,
    OP_OR   = 4'h3,
    OP_XOR  = 4'h4,
    OP_LDI  = 4'h5,
    OP_LD   = 4'h6,
    OP_ST   = 4'h7,
    OP_BEQZ = 4'h8,
    OP_JMP  = 4'h9,
    OP_HLT  = 4'hF;

  localparam [2:0]
    ALU_ADD   = 3'd0,
    ALU_SUB   = 3'd1,
    ALU_AND   = 3'd2,
    ALU_OR    = 3'd3,
    ALU_XOR   = 3'd4,
    ALU_PASSB = 3'd5;

  integer cyc = 0;
  always @(posedge clk) cyc <= cyc + 1;

  // Trace helper
  task trace;
    begin
      $display("T=%0t ns | cyc=%0d | op=%h z=%0b | IR=%0b A=%0b B=%0b AO=%0b MDR=%0b RW=%0b | MR=%0b MW=%0b M2R=%0b | PCW=%0b PCS=%0d AS=%0b | ASA=%0d ASB=%0d ALUOp=%0d | Halt=%0b",
        $time, cyc, opcode, zero,
        IRload, Aload, Bload, ALUOutLoad, MDRload, RegWrite,
        MemRead, MemWrite, MemToReg,
        PCWrite, PCSel, AddrSel,
        ALUSrcA, ALUSrcB, ALUOp,
        Halt);
    end
  endtask

  task step;
    begin
      @(posedge clk);
      #1 trace();
    end
  endtask

  // Issue an instruction: advance to S_IF2 and S_ID with given opcode/zero
  task issue_instruction;
    input [3:0] op;
    input       z;
    begin
      // We assume we're at S_IF1 at entry.
      step();               // S_IF2
      opcode = op;
      zero   = z;
      step();               // S_ID (opcode seen)
    end
  endtask

  // Soft checks (print warnings only)
  task expect;
    input cond;
    input [256*8-1:0] msg;
    begin
      if (!cond) $display("  [WARN] %s", msg);
    end
  endtask

  initial begin
    $dumpfile("simulations/control_unit_tb.vcd");
    $dumpvars(0, tb_control_unit);

    opcode = OP_ADD;
    zero   = 1'b0;

    // Keep reset high for 2 cycles
    repeat (2) step();
    reset = 1'b0;
    $display("== Release reset ==");

    // At this point, controller will be at S_IF1 on next step
    trace();

    // 1) ADD
    $display("\n== Test: ADD ==");
    issue_instruction(OP_ADD, 1'b0);
    step(); // S_EX_R
    expect(ALUOutLoad==1 && ALUSrcA==2'b01 && ALUSrcB==2'b00, "ADD: expected A/B to ALU and ALUOutLoad");
    step(); // S_WB_R
    expect(RegWrite==1 && MemToReg==0, "ADD: expected RegWrite from ALUOut");
    step(); // back to IF1

    // 2) LDI
    $display("\n== Test: LDI ==");
    issue_instruction(OP_LDI, 1'b0);
    step(); // S_EX_LDI
    expect(ALUOutLoad==1 && ALUOp==ALU_PASSB && ALUSrcB==2'b10, "LDI: PASSB(imm) into ALUOut");
    step(); // S_WB_LDI
    expect(RegWrite==1 && MemToReg==0, "LDI: writeback from ALUOut");
    step();

    // 3) LD
    $display("\n== Test: LD ==");
    issue_instruction(OP_LD, 1'b0);
    step(); // S_EA_LD
    expect(ALUOutLoad==1 && ALUOp==ALU_PASSB && ALUSrcB==2'b10, "LD: EA <- imm");
    step(); // S_MEM_LD
    expect(MemRead==1 && AddrSel==1 && MDRload==1, "LD: MemRead @ ALUOut, MDRload");
    step(); // S_WB_LD
    expect(RegWrite==1 && MemToReg==1, "LD: writeback from MDR");
    step();

    // 4) ST
    $display("\n== Test: ST ==");
    issue_instruction(OP_ST, 1'b0);
    step(); // S_EA_ST
    expect(ALUOutLoad==1 && ALUOp==ALU_PASSB && ALUSrcB==2'b10, "ST: EA <- imm");
    step(); // S_MEM_ST
    expect(MemWrite==1 && AddrSel==1, "ST: MemWrite @ ALUOut");
    step();

    // 5) BEQZ not taken
    $display("\n== Test: BEQZ not taken ==");
    issue_instruction(OP_BEQZ, 1'b0);
    step(); // one cycle after S_ID back to IF
    expect(PCWrite==0, "BEQZ not taken: PCWrite should be 0");
    step();

    // 6) BEQZ taken (controller applies PCWrite during the subsequent fetch window)
    $display("\n== Test: BEQZ taken ==");
    issue_instruction(OP_BEQZ, /*zero*/1'b1);

    // step once: we exit S_ID back to fetch
    step();

    // allow up to a few cycles for the controller to assert PCWrite with branch target
    seen_branch = 1'b0;
    begin: FIND_BRANCH
        for (k = 0; k < 4; k = k + 1) begin
            if (PCWrite && PCSel == 2'b01) begin
                seen_branch = 1;
                disable FIND_BRANCH; // verilog's 'break' out of this named block
        end
        step();
        end
    end
    expect(seen_branch, "BEQZ taken: expected PCWrite with branch target within next few cycles");


    // 7) JMP
    $display("\n== Test: JMP ==");
    issue_instruction(OP_JMP, 1'b0);
    step(); // cycle after S_ID
    expect(PCWrite==1 && PCSel==2'b10, "JMP: PCWrite with jump immediate");
    step();

    // 8) HLT
    $display("\n== Test: HLT ==");
    issue_instruction(OP_HLT, 1'b0);
    step(); // S_HALT
    expect(Halt==1, "HLT: Halt must be 1");
    step(); step();

    $display("\n== TB done ==");
    $finish;
  end

endmodule

sim/waveforms/control_unit_tb.vcd
$date
	Sat Nov 15 19:37:27 2025
$end
$version
	Icarus Verilog
$end
$timescale
	1s
$end
$scope module tb_control_unit $end
$var wire 1 ! RegWrite $end
$var wire 1 " PCWrite $end
$var wire 2 # PCSel [1:0] $end
$var wire 1 $ MemWrite $end
$var wire 1 % MemToReg $end
$var wire 1 & MemRead $end
$var wire 1 ' MDRload $end
$var wire 1 ( IRload $end
$var wire 1 ) Halt $end
$var wire 1 * Bload $end
$var wire 1 + Aload $end
$var wire 1 , AddrSel $end
$var wire 2 - ALUSrcB [1:0] $end
$var wire 2 . ALUSrcA [1:0] $end
$var wire 1 / ALUOutLoad $end
$var wire 3 0 ALUOp [2:0] $end
$var parameter 3 1 ALU_ADD $end
$var parameter 3 2 ALU_AND $end
$var parameter 3 3 ALU_OR $end
$var parameter 3 4 ALU_PASSB $end
$var parameter 3 5 ALU_SUB $end
$var parameter 3 6 ALU_XOR $end
$var parameter 4 7 OP_ADD $end
$var parameter 4 8 OP_AND $end
$var parameter 4 9 OP_BEQZ $end
$var parameter 4 : OP_HLT $end
$var parameter 4 ; OP_JMP $end
$var parameter 4 < OP_LD $end
$var parameter 4 = OP_LDI $end
$var parameter 4 > OP_OR $end
$var parameter 4 ? OP_ST $end
$var parameter 4 @ OP_SUB $end
$var parameter 4 A OP_XOR $end
$var reg 1 B clk $end
$var reg 4 C opcode [3:0] $end
$var reg 1 D reset $end
$var reg 1 E seen_branch $end
$var reg 1 F zero $end
$var integer 32 G cyc [31:0] $end
$var integer 32 H k [31:0] $end
$scope module dut $end
$var wire 1 B clk $end
$var wire 4 I opcode [3:0] $end
$var wire 1 D reset $end
$var wire 1 F zero $end
$var parameter 3 J ALU_ADD $end
$var parameter 3 K ALU_AND $end
$var parameter 3 L ALU_OR $end
$var parameter 3 M ALU_PASSB $end
$var parameter 3 N ALU_SUB $end
$var parameter 3 O ALU_XOR $end
$var parameter 4 P OP_ADD $end
$var parameter 4 Q OP_AND $end
$var parameter 4 R OP_BEQZ $end
$var parameter 4 S OP_HLT $end
$var parameter 4 T OP_JMP $end
$var parameter 4 U OP_LD $end
$var parameter 4 V OP_LDI $end
$var parameter 4 W OP_OR $end
$var parameter 4 X OP_ST $end
$var parameter 4 Y OP_SUB $end
$var parameter 4 Z OP_XOR $end
$var parameter 4 [ S_EA_LD $end
$var parameter 4 \ S_EA_ST $end
$var parameter 4 ] S_EX_LDI $end
$var parameter 4 ^ S_EX_R $end
$var parameter 4 _ S_HALT $end
$var parameter 4 ` S_ID $end
$var parameter 4 a S_IF1 $end
$var parameter 4 b S_IF2 $end
$var parameter 4 c S_MEM_LD $end
$var parameter 4 d S_MEM_ST $end
$var parameter 4 e S_WB_LD $end
$var parameter 4 f S_WB_LDI $end
$var parameter 4 g S_WB_R $end
$var reg 3 h ALUOp [2:0] $end
$var reg 1 / ALUOutLoad $end
$var reg 2 i ALUSrcA [1:0] $end
$var reg 2 j ALUSrcB [1:0] $end
$var reg 1 , AddrSel $end
$var reg 1 + Aload $end
$var reg 1 * Bload $end
$var reg 1 ) Halt $end
$var reg 1 ( IRload $end
$var reg 1 ' MDRload $end
$var reg 1 & MemRead $end
$var reg 1 % MemToReg $end
$var reg 1 $ MemWrite $end
$var reg 2 k PCSel [1:0] $end
$var reg 1 " PCWrite $end
$var reg 1 ! RegWrite $end
$var reg 4 l next [3:0] $end
$var reg 4 m state [3:0] $end
$upscope $end
$scope begin FIND_BRANCH $end
$upscope $end
$scope task expect $end
$var reg 1 n cond $end
$var reg 2048 o msg [2047:0] $end
$upscope $end
$scope task issue_instruction $end
$var reg 4 p op [3:0] $end
$var reg 1 q z $end
$upscope $end
$scope task step $end
$upscope $end
$scope task trace $end
$upscope $end
$upscope $end
$enddefinitions $end
$comment Show the parameter values. $end
$dumpall
b100 g
b110 f
b1001 e
b1011 d
b1000 c
b1 b
b0 a
b10 `
b1111 _
b11 ^
b101 ]
b1010 \
b111 [
b100 Z
b1 Y
b111 X
b11 W
b101 V
b110 U
b1001 T
b1111 S
b1000 R
b10 Q
b0 P
b100 O
b1 N
b101 M
b11 L
b10 K
b0 J
b100 A
b1 @
b111 ?
b11 >
b101 =
b110 <
b1001 ;
b1111 :
b1000 9
b10 8
b0 7
b100 6
b1 5
b101 4
b11 3
b10 2
b0 1
$end
#0
$dumpvars
xq
bx p
bx o
xn
b0 m
b1 l
b0 k
b1 j
b0 i
b0 h
b0 I
bx H
b0 G
0F
xE
1D
b0 C
0B
b0 0
1/
b0 .
b1 -
0,
0+
0*
0)
0(
0'
1&
0%
0$
b0 #
0"
0!
$end
#5
b1 G
1B
#10
0B
#15
b10 G
1B
#16
0q
b0 p
0D
#20
0B
#25
b10 l
1"
1(
b0 -
b0 j
0&
0/
b1 m
b11 G
1B
#30
0B
#35
b11 l
1*
1+
0"
0(
b10 m
b100 G
1B
#40
0B
#45
b100 l
1/
b1 .
b1 i
0*
0+
b11 m
b101 G
1B
#46
b10000010100010001000100001110100010000001100101011110000111000001100101011000110111010001100101011001000010000001000001001011110100001000100000011101000110111100100000010000010100110001010101001000000110000101101110011001000010000001000001010011000101010101001111011101010111010001001100011011110110000101100100 o
1n
#50
0B
#55
b0 l
1!
b0 .
b0 i
0/
b100 m
b110 G
1B
#56
b1000001010001000100010000111010001000000110010101111000011100000110010101100011011101000110010101100100001000000101001001100101011001110101011101110010011010010111010001100101001000000110011001110010011011110110110100100000010000010100110001010101010011110111010101110100 o
#60
0B
#65
b1 l
1/
b1 -
b1 j
1&
0!
b0 m
b111 G
1B
#66
b101 p
#70
0B
#75
b10 l
1"
1(
b0 -
b0 j
0&
0/
b1 m
b1000 G
1B
#76
b10 l
1"
1(
b101 C
b101 I
#80
0B
#85
b101 l
1*
1+
0"
0(
b10 m
b1001 G
1B
#90
0B
#95
b110 l
1/
b101 0
b101 h
b10 -
b10 j
b10 .
b10 i
0*
0+
b101 m
b1010 G
1B
#96
b10011000100010001001001001110100010000001010000010000010101001101010011010000100010100001101001011011010110110100101001001000000110100101101110011101000110111100100000010000010100110001010101010011110111010101110100 o
#100
0B
#105
b0 l
1!
b0 0
b0 h
b0 -
b0 j
b0 .
b0 i
0/
b110 m
b1011 G
1B
#106
b100110001000100010010010011101000100000011101110111001001101001011101000110010101100010011000010110001101101011001000000110011001110010011011110110110100100000010000010100110001010101010011110111010101110100 o
#110
0B
#115
b1 l
1/
b1 -
b1 j
1&
0!
b0 m
b1100 G
1B
#116
b110 p
#120
0B
#125
b10 l
1"
1(
b0 -
b0 j
0&
0/
b1 m
b1101 G
1B
#126
b10 l
1"
1(
b110 C
b110 I
#130
0B
#135
b111 l
1*
1+
0"
0(
b10 m
b1110 G
1B
#140
0B
#145
b1000 l
1/
b101 0
b101 h
b10 -
b10 j
b10 .
b10 i
0*
0+
b111 m
b1111 G
1B
#146
b1001100010001000011101000100000010001010100000100100000001111000010110100100000011010010110110101101101 o
#150
0B
#155
b1001 l
1'
1&
1,
b0 0
b0 h
b0 -
b0 j
b0 .
b0 i
0/
b1000 m
b10000 G
1B
#156
b100110001000100001110100010000001001101011001010110110101010010011001010110000101100100001000000100000000100000010000010100110001010101010011110111010101110100001011000010000001001101010001000101001001101100011011110110000101100100 o
#160
0B
#165
b0 l
1%
1!
0,
0&
0'
b1001 m
b10001 G
1B
#166
b1001100010001000011101000100000011101110111001001101001011101000110010101100010011000010110001101101011001000000110011001110010011011110110110100100000010011010100010001010010 o
#170
0B
#175
b1 l
1/
b1 -
b1 j
1&
0%
0!
b0 m
b10010 G
1B
#176
b111 p
#180
0B
#185
b10 l
1"
1(
b0 -
b0 j
0&
0/
b1 m
b10011 G
1B
#186
b10 l
1"
1(
b111 C
b111 I
#190
0B
#195
b1010 l
1*
1+
0"
0(
b10 m
b10100 G
1B
#200
0B
#205
b1011 l
1/
b101 0
b101 h
b10 -
b10 j
b10 .
b10 i
0*
0+
b1010 m
b10101 G
1B
#206
b1010011010101000011101000100000010001010100000100100000001111000010110100100000011010010110110101101101 o
#210
0B
#215
b0 l
1$
1,
b0 0
b0 h
b0 -
b0 j
b0 .
b0 i
0/
b1011 m
b10110 G
1B
#216
b10100110101010000111010001000000100110101100101011011010101011101110010011010010111010001100101001000000100000000100000010000010100110001010101010011110111010101110100 o
#220
0B
#225
b1 l
1/
b1 -
b1 j
1&
0,
0$
b0 m
b10111 G
1B
#226
b1000 p
#230
0B
#235
b10 l
1"
1(
b0 -
b0 j
0&
0/
b1 m
b11000 G
1B
#236
b10 l
1"
1(
b1000 C
b1000 I
#240
0B
#245
b0 l
1/
b10 -
b10 j
1*
1+
0"
0(
b10 m
b11001 G
1B
#250
0B
#255
b1 l
1&
b1 -
b1 j
1/
0*
0+
b0 m
b11010 G
1B
#256
b100001001000101010100010101101000100000011011100110111101110100001000000111010001100001011010110110010101101110001110100010000001010000010000110101011101110010011010010111010001100101001000000111001101101000011011110111010101101100011001000010000001100010011001010010000000110000 o
#260
0B
#265
b10 l
1"
1(
b0 -
b0 j
0&
0/
b1 m
b11011 G
1B
#266
1q
#270
0B
#275
b0 l
1/
b10 -
b10 j
1*
1+
0"
0(
b10 m
b11100 G
1B
#276
b1 #
b1 k
1"
b0 l
b10 -
b10 j
1/
1*
1+
1F
#280
0B
#285
b1 l
1&
b0 #
b0 k
0"
b1 -
b1 j
1/
0*
0+
b0 m
b11101 G
1B
#290
0B
#295
b10 l
1"
1(
b0 -
b0 j
0&
0/
b1 m
b11110 G
1B
#296
b0 H
0E
#300
0B
#305
b0 l
b1 #
b1 k
1/
b10 -
b10 j
1*
1+
1"
0(
b10 m
b11111 G
1B
#306
0q
b1001 p
b1000010010001010101000101011010001000000111010001100001011010110110010101101110001110100010000001100101011110000111000001100101011000110111010001100101011001000010000001010000010000110101011101110010011010010111010001100101001000000111011101101001011101000110100000100000011000100111001001100001011011100110001101101000001000000111010001100001011100100110011101100101011101000010000001110111011010010111010001101000011010010110111000100000011011100110010101111000011101000010000001100110011001010111011100100000011000110111100101100011011011000110010101110011 o
1E
b1 H
#310
0B
#315
b1 l
1&
b0 #
b0 k
0"
b1 -
b1 j
1/
0*
0+
b0 m
b100000 G
1B
#316
b1 l
b1 -
b1 j
1&
1/
0F
b1001 C
b1001 I
#320
0B
#325
b10 l
1"
1(
b0 -
b0 j
0&
0/
b1 m
b100001 G
1B
#330
0B
#335
b0 l
b10 #
b10 k
1*
1+
1"
0(
b10 m
b100010 G
1B
#336
b100101001001101010100000011101000100000010100000100001101010111011100100110100101110100011001010010000001110111011010010111010001101000001000000110101001110101011011010111000000100000011010010110110101101101011001010110010001101001011000010111010001100101 o
#340
0B
#345
b1 l
1/
b1 -
b1 j
1&
b0 #
b0 k
0"
0*
0+
b0 m
b100011 G
1B
#346
b1111 p
#350
0B
#355
b10 l
1"
1(
b0 -
b0 j
0&
0/
b1 m
b100100 G
1B
#356
b10 l
1"
1(
b1111 C
b1111 I
#360
0B
#365
b1111 l
1)
1*
1+
0"
0(
b10 m
b100101 G
1B
#370
0B
#375
1)
0*
0+
b1111 m
b100110 G
1B
#376
b1001000010011000101010000111010001000000100100001100001011011000111010000100000011011010111010101110011011101000010000001100010011001010010000000110001 o
#380
0B
#385
b100111 G
1B
#390
0B
#395
b101000 G
1B
