regfile.v
// 8 registers R0-R7, 16 bits each so 8x16 register file
// read from the regiser so for reading we output the data to be read for the specified register (to be input to ALU for eg)
// write to the registers so for writing we accept as an input the data to write (writeData) [as a result of ALU computation - to update reg for eg]
// if write enable == 1 then we are trying to write something into a particular register so we accept that value and put it into the specified register
module regfile(regSource1, regSource2, regDestination, writeData, data1, data2, writeEnable, clock, reset);
    input clock, reset, writeEnable;
    input [2:0] regSource1;
    input [2:0] regSource2;
    input [2:0] regDestination;

    input [15:0] writeData;

    output [15:0] data1;
    output [15:0] data2;

    reg [15:0] registers [0:7]; // R0-R7 each of size 16 bits (registers)

    integer i;

    always @(posedge clock) begin
        if (reset)
            begin
                // initialize registers to 0 initially
                for (i=0; i<8; i=i+1)
                    registers[i] <= 16'b0000_0000_0000_0000;
                display_memory_content(); // displays the initial content of the register
            end
        
        else if (writeEnable && regDestination != 3'b000) // if writing enabled then write the data from 'writeData' to the specified destination register like MOV
            registers[regDestination] <= writeData;
    end



    task display_memory_content(); 
        // variables for writing memory content to a file
        integer f; // file handler
        integer j; // memory location counter

        begin
            f = $fopen("register_content.txt", "w"); // open the file for writing
            for (j = 0; j < 8; j++) begin
                $fwrite(f, "R%1d: %04h\n", j, registers[j]);  // addr: data
            end
            $fclose(f); // close the file        
        end
    endtask

    always @(negedge clock) begin
        if (writeEnable && regDestination != 3'b000)
            display_memory_content();
    end


    /* Using the same register as the destination and source
        ADD R1, R1, R2;  -> R1 = R1 + R2 
        
        If that is the instruction we have for example, the control unit will be requesting to get/read the values of registers R1 and R2 to
        be provided as inputs to the ALU first. (regSource1=3'b001 and regSource2=3'b010 and writeEnable=0)
        This will mean data1 will have value of R1 (old val before addition operation) and data2=R2
        the operation will be carried out by the ALU and the result=R1+R2 written(writeData=result and writeEnable=1) back to R1. 
    */


    // To read the register values and provide them as an output for a different module to work with
    // Read means the callee expects to get the value stored in the register specified by the argument to the module 
    assign data1 = (regSource1==3'b000) ? 16'b0000_0000_0000_0000: registers[regSource1]; // Hardwiring R0 to 0
    assign data2 = (regSource2==3'b000) ? 16'b0000_0000_0000_0000: registers[regSource2];

endmodule

tb/regfile_tb.v
`include "regfile.v"

module regfile_tb;
    reg [2:0] regSource1, regSource2, regDestination;
    reg [15:0] writeData;
    reg clock = 1'b1, reset, writeEnable;

    wire [15:0] data1, data2;

    regfile myregisters(.regSource1(regSource1), .regSource2(regSource2), .regDestination(regDestination), .writeData(writeData), .data1(data1), .data2(data2), .writeEnable(writeEnable), .clock(clock), .reset(reset));

    always #5 clock = ~clock;

    initial begin
    // generate files needed to plot the waveform using GTKWave
        $dumpfile("sim/waveforms/reg_file_wavedata.vcd");
		$dumpvars(0, regfile_tb);

        // Initial setup
        reset = 1'b1; // sets all registers to 0
        writeEnable = 1'b0;

        @(negedge clock); // wait until just the next pos edge (effectively #5 -> the period)
        
        // release the reset to start operation
        reset = 1'b0; 


        // --- Write 1: Store 0x23FE into R2 ---
        @(negedge clock) // prepare inputs on negative edge
        regDestination = 3'b010; // R2
        writeData = 16'h23FE; // R2 = 0x23fe
        writeEnable = 1'b1;

        // The write happens on the *next* immediate posedge clock

        @(negedge clock); // Wait for the next negedge to disable write
        writeEnable = 1'b0; // Clear write enable

        @(negedge clock); // After the write, set up read source
        regSource1 = 3'b010; // Check value of R2 (should see 0x23FE on data1 immediately)


        // --- Write 2: Store 0x6781 into R4 ---
        @(negedge clock); // Prepare inputs
        regDestination = 3'b100; // R4
        writeData = 16'h6781; 
        writeEnable = 1'b1; 

        regSource1 = 3'b100; // Check R4 value right away in data1

        @(negedge clock);
        writeEnable = 1'b0; 

        // data1 should now hold 0x6781 (read asynchronously)


         // --- Test R0: Attempt to write to R0 (should fail) ---
         @(negedge clock);
        regDestination = 3'b000; // Try to write to R0
        writeData = 16'hFFFF;    // Value we want to write
        writeEnable = 1'b1;

        @(negedge clock);
        writeEnable = 1'b0;

        @(negedge clock);
        regSource1 = 3'b000; // Read R0 (data1 should remain 0x0000, not 0xFFFF)

       @(negedge clock);

       $display("Simulation finished.");
       $finish;
       #2;
    end
endmodule

sim/waveforms/reg_file_wavedata.vcd
$date
	Thu Nov 20 19:02:24 2025
$end
$version
	Icarus Verilog
$end
$timescale
	1s
$end
$scope module regfile_tb $end
$var wire 16 ! data2 [15:0] $end
$var wire 16 " data1 [15:0] $end
$var reg 1 # clock $end
$var reg 3 $ regDestination [2:0] $end
$var reg 3 % regSource1 [2:0] $end
$var reg 3 & regSource2 [2:0] $end
$var reg 1 ' reset $end
$var reg 16 ( writeData [15:0] $end
$var reg 1 ) writeEnable $end
$scope module myregisters $end
$var wire 1 # clock $end
$var wire 3 * regDestination [2:0] $end
$var wire 3 + regSource1 [2:0] $end
$var wire 3 , regSource2 [2:0] $end
$var wire 1 ' reset $end
$var wire 16 - writeData [15:0] $end
$var wire 1 ) writeEnable $end
$var wire 16 . data2 [15:0] $end
$var wire 16 / data1 [15:0] $end
$var integer 32 0 i [31:0] $end
$scope task display_memory_content $end
$var integer 32 1 f [31:0] $end
$var integer 32 2 j [31:0] $end
$upscope $end
$upscope $end
$upscope $end
$enddefinitions $end
$comment Show the parameter values. $end
$dumpall
$end
#0
$dumpvars
b1000 2
b10000000000000000000000000000011 1
b1000 0
bx /
bx .
bx -
bx ,
bx +
bx *
0)
bx (
1'
bx &
bx %
bx $
1#
bx "
bx !
$end
#5
0'
0#
#10
1#
#15
1)
b10001111111110 (
b10001111111110 -
b10 $
b10 *
0#
#20
1#
#25
0)
0#
#30
1#
#35
b10001111111110 "
b10001111111110 /
b10 %
b10 +
0#
#40
1#
#45
b0 "
b0 /
b1000 2
b100 %
b100 +
1)
b110011110000001 (
b110011110000001 -
b100 $
b100 *
0#
#50
b110011110000001 "
b110011110000001 /
1#
#55
b1000 2
0)
0#
#60
1#
#65
1)
b1111111111111111 (
b1111111111111111 -
b0 $
b0 *
0#
#70
1#
#75
0)
0#
#80
1#
#85
b0 "
b0 /
b0 %
b0 +
0#
