src/memory.v
module memory(clock, enable, writeEnable, address, writeData, readData);
    input clock, enable, writeEnable;
    input [7:0] address;
    input [15:0] writeData;
    output wire [15:0] readData;

    // Initially we planned to make use of all the bits for the memory -> 65,536 x 16-bit memory array -> but this was too much to work with so we reduced it to 256 
    reg [15:0] mem[0:255];  // but we are going to make it 256 memory locations X each storing 16-bit

    // load memory content from program.hex
    initial begin
        $readmemh("program.hex", mem);  // Then load 16-bit words, one per line
        display_memory_content(); // begin by displaying the memory content in the file
        // $writememh("memory_content.txt", mem); // alternative

    end

    task display_memory_content(); 
        // variables for writing memory content to a file
        integer f; // file handler
        integer j; // memory location counter

        begin
            f = $fopen("memory_content.txt", "w"); // open the file for writing
            for (j = 0; j < 256; j++) begin
                $fwrite(f, "%02d: %04h\n", j[7:0], mem[j]);  // addr: data
            end
            $fclose(f); // close the file        
        end
    endtask


    // write the content of the RAM memory to a file
    always @ (posedge clock) begin
        if (enable && writeEnable) begin
            mem[address] <= writeData; // write to the RAM at given address
            // #1 $writememh("memory_content.txt", mem); // alternative

            // #1 display_memory_content(); // update the memory content file accordingly
        end
    end

    // taken out of the above always block to avoid a race condition between the displaying and writing to the RAM which would be scheduled for the same time (posedge of the clock) so we write to the RAM on the posedge of the clock and display the updates on the following negedge
    always @(negedge clock) begin
        if (enable && writeEnable) begin
            display_memory_content();
        end
    end

    // read from and write to memory when enabled -- replaced by the lines below for faster and simpler simulation but better to keep for hardware implementation as block RAMs are inherently synchronous (both read and write with the clock)
/*    always @(posedge clock) begin
        if (enable) begin
            if (writeEnable)
                mem[address] <= writeData;
            else
                readData <= mem[address];
        end
    end
*/

    // asynchronous read when enabled 
    assign readData = enable ? mem[address] : 16'h0000;

endmodule

memory_tb.v
`include "memory.v"

module memory_tb;
    reg [7:0] address;
    reg [15:0] writeData;
    reg clock = 1'b1, enable, writeEnable;

    wire [15:0] readData;

    memory myMemory(.clock(clock), .enable(enable), .writeEnable(writeEnable), .address(address), .writeData(writeData), .readData(readData));

    always #5 clock = ~clock;

    initial begin
    // generate files needed to plot the waveform using GTKWave
        $dumpfile("simulations/memory_wavedata.vcd");
		$dumpvars(0, memory_tb);

        // assign values with time to input signals to see output
        enable = 1'b1;
        writeEnable = 1'b0;
        address = 8'h00;

        // Wait for the first negative edge to start operations -- basically #5 but synchronizes it well
        @(negedge clock); 


        // ---- Reading - read the first 5 elements from the memory ------
        // We set up the address on the negative edge, 
        // the module reads the data on the *next* positive edge.
        repeat (4) begin 
            @(negedge clock); address = address + 1'b1;
        end
        // At this point, several clock cycles have passed and memory_content.txt has been initialized once.


// ---- Writing 1 -------
        @(negedge clock); 
        writeEnable = 1'b1; // Turn on write mode
        address = 8'h0F;    // Address 15
        writeData = 16'hFA2D; 

        @(negedge clock);   // Wait for one more negative edge (the write happens on the posedge in between)
        writeEnable = 1'b0; // Turn off write mode

        @(negedge clock);
        address = 8'h0F;    // Read back address 15 (check readData wire after posedge clock)

        // 2nd write 
        @(negedge clock); 
        writeEnable = 1'b1;
        address = 8'h0C;    // Address 12
        writeData = 16'h2231; 

        @(negedge clock); 
        writeEnable = 1'b0;

        @(negedge clock);
        address = 8'h0C;    // Read back address 12

        // 3rd write 
        @(negedge clock); 
        writeEnable = 1'b1;
        address = 8'h14;    // Address 20
        writeData = 16'h9999; 

        @(negedge clock); 
        writeEnable = 1'b0;

        @(negedge clock);
        address = 8'h14;    // Read back address 20

        @(negedge clock);
        #1;
        $display("Simulation finished.");
        $finish;
    end
endmodule

simulations/memory_wavedata.vcd
$date
	Thu Nov 20 17:55:32 2025
$end
$version
	Icarus Verilog
$end
$timescale
	1s
$end
$scope module memory_tb $end
$var wire 16 ! readData [15:0] $end
$var reg 8 " address [7:0] $end
$var reg 1 # clock $end
$var reg 1 $ enable $end
$var reg 16 % writeData [15:0] $end
$var reg 1 & writeEnable $end
$scope module myMemory $end
$var wire 8 ' address [7:0] $end
$var wire 1 # clock $end
$var wire 1 $ enable $end
$var wire 16 ( writeData [15:0] $end
$var wire 1 & writeEnable $end
$var wire 16 ) readData [15:0] $end
$scope task display_memory_content $end
$var integer 32 * f [31:0] $end
$var integer 32 + j [31:0] $end
$upscope $end
$upscope $end
$upscope $end
$enddefinitions $end
$comment Show the parameter values. $end
$dumpall
$end
#0
$dumpvars
b100000000 +
b10000000000000000000000000000011 *
b101001000000101 )
bx (
b0 '
0&
bx %
1$
1#
b0 "
b101001000000101 !
$end
#5
0#
#10
1#
#15
b101010000000011 !
b101010000000011 )
b1 "
b1 '
0#
#20
1#
#25
b11001010000 !
b11001010000 )
b10 "
b10 '
0#
#30
1#
#35
b111000000111000 !
b111000000111000 )
b11 "
b11 '
0#
#40
1#
#45
b110100000100000 !
b110100000100000 )
b100 "
b100 '
0#
#50
1#
#55
bx !
bx )
b1111101000101101 %
b1111101000101101 (
b1111 "
b1111 '
1&
0#
#60
b1111101000101101 !
b1111101000101101 )
1#
#65
0&
0#
#70
1#
#75
0#
#80
1#
#85
bx !
bx )
b100000000 +
b10001000110001 %
b10001000110001 (
b1100 "
b1100 '
1&
0#
#90
b10001000110001 !
b10001000110001 )
1#
#95
b100000000 +
0&
0#
#100
1#
#105
0#
#110
1#
#115
bx !
bx )
b100000000 +
b1001100110011001 %
b1001100110011001 (
b10100 "
b10100 '
1&
0#
#120
b1001100110011001 !
b1001100110011001 )
1#
#125
b100000000 +
0&
0#
