memory.v
module memory(clock, enable, writeEnable, address, writeData, readData);
    input clock, enable, writeEnable;
    input [15:0] address;
    input [15:0] writeData;
    output reg [15:0] readData;

    reg [15:0] mem[0:65535]; // 65,536 x 16-bit memory array

    // load memory content from program.hex
    integer i;
    initial begin
        for (i = 0; i < 65536; i = i + 1) // first clear all to 0
            mem[i] = 16h'0000;
      $readmemh("program.hex", mem);  // Then load 16-bit words, one per line
    end

    // read from and write to memory when enabled
    always @(posedge clock) begin
        if (enable) begin
            if (writeEnable)
                mem[address] <= writeData;
            else
                readData = [address];
        end
    end
    

endmodule

memory_tb.v
`include "memory.v"

module memory_tb;
    reg [15:0] address, writeData;
    reg clock = 1'b1, enable, writeEnable;

    wire [15:0] readData;

    memory myMemory(.clock(clock), .enable(enable), .writeEnable(writeEnable), .address(address), .writeData(writeData), .readData(readData));

    initial begin
    // generate files needed to plot the waveform using GTKWave
        $dumpfile("simulations/memory_wavedata.vcd");
		$dumpvars(0, memory_tb);

        // assign values with time to input signals to see output
        enable = 1'b1;
        writeEnable = 1'b0;

// ---- Reading ------
        #10
        address = 16'h0000; // memory[0]

        #10
        address = 16'h0001; // memory[1]

        #10
        address = 16'h0002; // memory[2]

        #10
        address = 16'h0003; // memory[3]
        
// ---- Writing -------
        #10
        writeEnable = 1'b1;
        
        #10
        address = 16'h0005; 
        writeData = 16'hFA2D; // memory[5] = 0xFA2D;

        #10
        writeEnable = 1'b0;

        #10
        address = 16'h0005; // read val stored in memory[5]

        #10
        $finish;
    end


    always #5 clock = ~clock;

endmodule

simulations/memory_wavedata.vcd
$date
	Mon Nov  3 01:21:49 2025
$end
$version
	Icarus Verilog
$end
$timescale
	1s
$end
$scope module memory_tb $end
$var wire 16 ! readData [15:0] $end
$var reg 16 " address [15:0] $end
$var reg 1 # clock $end
$var reg 1 $ enable $end
$var reg 16 % writeData [15:0] $end
$var reg 1 & writeEnable $end
$scope module myMemory $end
$var wire 16 ' address [15:0] $end
$var wire 1 # clock $end
$var wire 1 $ enable $end
$var wire 16 ( writeData [15:0] $end
$var wire 1 & writeEnable $end
$var reg 16 ) readData [15:0] $end
$var integer 32 * i [31:0] $end
$upscope $end
$upscope $end
$enddefinitions $end
$comment Show the parameter values. $end
$dumpall
$end
#0
$dumpvars
b10000000000000000 *
bx )
bx (
bx '
0&
bx %
1$
1#
bx "
bx !
$end
#5
0#
#10
b110010000000101 !
b110010000000101 )
1#
b0 "
b0 '
#15
0#
#20
b110011000000011 !
b110011000000011 )
1#
b1 "
b1 '
#25
0#
#30
b1101000100011 !
b1101000100011 )
1#
b10 "
b10 '
#35
0#
#40
b111000000000000 !
b111000000000000 )
1#
b11 "
b11 '
#45
0#
#50
1#
1&
#55
0#
#60
1#
b1111101000101101 %
b1111101000101101 (
b101 "
b101 '
#65
0#
#70
b1111101000101101 !
b1111101000101101 )
1#
0&
