pc.v
module pc(clock, reset, next_address, current_address);
    input clock;
    input reset;
    input [7:0] next_address; // 8 bits because the memory is 8-bit addressed (256 locations)
    output reg [7:0] current_address;

    // Task to log PC changes to a file
    task log_pc_change();
        integer f_pc_log;
        // Use $fopen with "a" mode to APPEND to the file (prevents overwriting every time)
        begin
            f_pc_log = $fopen("PC_log.txt", "a"); 
            if (f_pc_log) begin
                $fwrite(f_pc_log, "Time: %0t ns | Next Addr: %h | Current Addr: %h\n", $time, next_address, current_address);
                $fclose(f_pc_log);
            end
        end
    endtask

    // The core logic behind our PC is a synchronous register with asynchronous reset
    always @(posedge clock or posedge reset) begin
        if (reset) begin
            current_address <= 8'h00; // Reset PC to the start of memory (address 0)
        end 
        else begin
            // Update the PC with the address provided by the control path
            current_address <= next_address;
        end
    end

    always @(negedge clock)
        log_pc_change();

endmodule

tb/pc_tb.v
`include "pc.v"

module pc_tb;
    reg clock, reset;
    reg [7:0] next_address;
    wire [7:0] current_address;

    pc my_pc(.clock(clock), .reset(reset), .next_address(next_address), .current_address(current_address));

    // Clock generator
    always #5 clock = ~clock;

    initial begin
        $dumpfile("sim/waveforms/pc_wavedata.vcd");
		$dumpvars(0, pc_tb);

        // Initial setup
        clock = 1'b0;
        reset = 1'b1; // Hold in reset
        next_address = 8'hFF; // Put some random value on input while in reset

        // --- Test 1: Reset Behavior ---
        // PC should go to 0x00 on the first positive clock edge
        #10; // Wait a little time to stabilize inputs
        reset = 1'b0; // Release reset

        // --- Test 2: Sequential Counting ---
        // The PC should now load whatever is on next_address on each posedge
        
        @(negedge clock); // Sync up to the negedge to change inputs safely
        next_address = 8'h01; 

        @(negedge clock);
        next_address = 8'h02;

        @(negedge clock);
        next_address = 8'h03;

        // --- Test 3: Jump to a New Address ---
        @(negedge clock);
        $display("Testing Jump/Branch functionality");
        next_address = 8'h20; // Simulate a jump instruction result

        @(negedge clock);
        next_address = 8'h21; // Check increment after jump

        @(negedge clock);
        next_address = 8'h22;

        #20;
        $display("Simulation finished.");
        $finish;
    end
endmodule

simulations/pc_wavedata.vcd
$date
	Thu Nov 20 19:49:49 2025
$end
$version
	Icarus Verilog
$end
$timescale
	1s
$end
$scope module pc_tb $end
$var wire 8 ! current_address [7:0] $end
$var reg 1 " clock $end
$var reg 8 # next_address [7:0] $end
$var reg 1 $ reset $end
$scope module my_pc $end
$var wire 1 " clock $end
$var wire 8 % next_address [7:0] $end
$var wire 1 $ reset $end
$var reg 8 & current_address [7:0] $end
$upscope $end
$upscope $end
$enddefinitions $end
$comment Show the parameter values. $end
$dumpall
$end
#0
$dumpvars
b0 &
b11111111 %
1$
b11111111 #
0"
b0 !
$end
#5
1"
#10
b1 #
b1 %
0"
0$
#15
b1 !
b1 &
1"
#20
b10 #
b10 %
0"
#25
b10 !
b10 &
1"
#30
b11 #
b11 %
0"
#35
b11 !
b11 &
1"
#40
b100000 #
b100000 %
0"
#45
b100000 !
b100000 &
1"
#50
b100001 #
b100001 %
0"
#55
b100001 !
b100001 &
1"
#60
b100010 #
b100010 %
0"
#65
b100010 !
b100010 &
1"
