regfile.v
// 8 registers R0-R7, 16 bits each so 8x16 register file
// read from the regiser so for reading we output the data to be read for the specified register (to be input to ALU for eg)
// write to the registers so for writing we accept as an input the data to write (writeData) as a result of ALU computation for eg
// if write enable == 1 then we are trying to write something into a particular register so we accept that value and put it into the specified register
module regfile(regSource1, regSource2, regDestination, writeData, data1, data2, writeEnable, clock, reset);
    input clock, reset, writeEnable;
    input [2:0] regSource1;
    input [2:0] regSource2;
    input [2:0] regDestination;

    input [15:0] writeData;

    output [15:0] data1;
    output [15:0] data2;

    reg [15:0] registers [0:7]; // R0-R7 each of size 16 bits (registers)

    integer i;

    always @(posedge clock) begin
        if (reset)
            begin
                // initialize registers to 0 initially
                for (i=0; i<8; i=i+1)
                    registers[i] <= 16'b0000_0000_0000_0000;    
            end
        
        else if (writeEnable && regDestination != 3'b000) // if writing enabled then write the data from 'writeData' to the specified destination register like MOV
            registers[regDestination] <= writeData;
    end


    /* Using the same register as the destination and source
        ADD R1, R1, R2;  -> R1 = R1 + R2 
        
        If that is the instruction we have for example, the control unit will be requesting to get/read the values of registers R1 and R2 to
        be provided as inputs to the ALU first. (regSource1=3'b001 and regSource2=3'b010 and writeEnable=0)
        This will mean data1 will have value of R1 (old val before addition operation) and data2=R2
        the operation will be carried out by the ALU and the result written(writeData=R1+R2 and writeEnable=1) back to R1. 
    */


    // To read the register values and provide them as an output for a different module to work with
    // Read means the callee expects to get the value stored in the register specified by the argument to the module 
    assign data1 = (regSource1==3'b000) ? 16'b0000_0000_0000_0000: registers[regSource1]; // Hardwiring R0 to 0
    assign data2 = (regSource2==3'b000) ? 16'b0000_0000_0000_0000: registers[regSource2];

endmodule

regfile_tb.v
`include "regfile.v"

module regfile_tb;
    reg [2:0] regSource1, regSource2, regDestination;
    reg [15:0] writeData;
    reg clock = 1'b1, reset, writeEnable;

    wire [15:0] data1, data2;

    regfile myregisters(.regSource1(regSource1), .regSource2(regSource2), .regDestination(regDestination), .writeData(writeData), .data1(data1), .data2(data2), .writeEnable(writeEnable), .clock(clock), .reset(reset));

    initial begin
    // generate files needed to plot the waveform using GTKWave
        $dumpfile("simulations/reg_file_wavedata.vcd");
		$dumpvars(0, regfile_tb);

        // assign values with time to input signals to see output
        reset = 1'b0;
        writeEnable = 1'b0;

        #4
        reset = 1'b1;
        regSource1 = 3'b000; // R0
        regSource2 = 3'b100; // R4

        #6
        reset = 1'b0;

        // Store into R2 0x23FE by selecting destination register as R2 and setting the writeData to the value and enabling the writeEnable signal

        #2
        regDestination = 3'b010; // R2
        writeData = 16'h23FE; // R2 = 0x23FE
        writeEnable = 1'b1;

        #7
        writeEnable = 1'b0;

        #1
        regSource1 = 3'b010; // R2 should have 0x23FE


        // Store into R4  0x6781
        #8
        regDestination = 3'b100; // select R4
        writeData = 16'h6781; // prepare val 0x6781
        writeEnable = 1'b1; // set write enable signal
        regSource1 = 3'b100; // check value of R4 immediately

        #8
        writeEnable = 1'b0; // clear enable signal 


        #10
        $finish;
    end


    always #4 clock = ~clock;

endmodule

simulations/reg_file_wavedata.vcd
$date
	Mon Oct 20 18:51:01 2025
$end
$version
	Icarus Verilog
$end
$timescale
	1s
$end
$scope module regfile_tb $end
$var wire 16 ! data2 [15:0] $end
$var wire 16 " data1 [15:0] $end
$var reg 1 # clock $end
$var reg 3 $ regDestination [2:0] $end
$var reg 3 % regSource1 [2:0] $end
$var reg 3 & regSource2 [2:0] $end
$var reg 1 ' reset $end
$var reg 16 ( writeData [15:0] $end
$var reg 1 ) writeEnable $end
$scope module myregisters $end
$var wire 1 # clock $end
$var wire 3 * regDestination [2:0] $end
$var wire 3 + regSource1 [2:0] $end
$var wire 3 , regSource2 [2:0] $end
$var wire 1 ' reset $end
$var wire 16 - writeData [15:0] $end
$var wire 1 ) writeEnable $end
$var wire 16 . data2 [15:0] $end
$var wire 16 / data1 [15:0] $end
$var integer 32 0 i [31:0] $end
$upscope $end
$upscope $end
$enddefinitions $end
$comment Show the parameter values. $end
$dumpall
$end
#0
$dumpvars
bx 0
bx /
bx .
bx -
bx ,
bx +
bx *
0)
bx (
0'
bx &
bx %
bx $
1#
bx "
bx !
$end
#4
b0 "
b0 /
0#
b100 &
b100 ,
b0 %
b0 +
1'
#8
b0 !
b0 .
b1000 0
1#
#10
0'
#12
1)
b10001111111110 (
b10001111111110 -
b10 $
b10 *
0#
#16
1#
#19
0)
#20
b10001111111110 "
b10001111111110 /
b10 %
b10 +
0#
#24
1#
#28
b0 "
b0 /
0#
b100 %
b100 +
1)
b110011110000001 (
b110011110000001 -
b100 $
b100 *
#32
b110011110000001 "
b110011110000001 /
b110011110000001 !
b110011110000001 .
1#
#36
0#
0)
